mux2/mux2.v
`timescale 1ns / 1ns

// ----------------------------------------------------------------
// Module   : mux2
// Author   : 平の路
// Function : mux2
// ----------------------------------------------------------------
module mux2 (
    // input  wire clk,      // 系统时钟
    // input  wire rst_n,    // 低电平异步复位
    input  wire a,       // 用户输入端口
    input  wire b,       // 用户输入端口
    input  wire set,       // 用户输入端口
    output  out        // 用户输出端口
);

    // 内部信号定义
    assign out =(set==0)?a:b;

    // 物理时序逻辑电路设计区
    // always @(posedge clk or negedge rst_n)
    // begin
    //     if (!rst_n)
    //         begin
    //             out <= 1'b0;
    //         end
    //     else
    //         begin

    //         end
    // end

endmodule

mux2/mux2_tb.v
`timescale 1ns / 1ns

// ----------------------------------------------------------------
// Module   : mux2_tb
// Author   : 平の路
// Function : mux2_tb
// ----------------------------------------------------------------
module mux2_tb ();

    reg a1;
    reg b1;
    reg set1;
    wire out1;

mux2 mux2_inst0(
    .a(a1),       // 用户输入端口
    .b(b1),       // 用户输入端口
    .set(set1),       // 用户输入端口
    .out(out1)        // 用户输出端口
);
    // 内部信号定义

initial begin
    $dumpfile("wave.vcd");          //指定波形数据库的文件名
    $dumpvars(0, mux2_tb);          //测试的目标文件

    a1=0;b1=0;set1=0;
    #20;

    a1=0;b1=1;set1=0;
    #20;

    a1=1;b1=0;set1=0;
    #20;

    a1=1;b1=1;set1=0;
    #20;

    a1=0;b1=0;set1=1;
    #20;

    a1=0;b1=1;set1=1;
    #20;

    a1=1;b1=0;set1=1;
    #20;

    a1=1;b1=1;set1=1;
    #20;
    $finish;
end

    // 物理时序逻辑电路设计区
    // always @(posedge clk or negedge rst_n) begin
    //     if (!rst_n) begin
    //          <= 1'b0;
    //     end else begin

    //     end
    // end

endmodule

mux2/wave.vcd
$date
	Wed Sep 23 14:24:09 2026
$end
$version
	Icarus Verilog
$end
$timescale
	1ns
$end
$scope module mux2_tb $end
$var wire 1 ! out1 $end
$var reg 1 " a1 $end
$var reg 1 # b1 $end
$var reg 1 $ set1 $end
$scope module mux2_inst0 $end
$var wire 1 " a $end
$var wire 1 # b $end
$var wire 1 $ set $end
$var wire 1 ! out $end
$upscope $end
$upscope $end
$enddefinitions $end
$comment Show the parameter values. $end
$dumpall
$end
#0
$dumpvars
0$
0#
0"
0!
$end
#20
1#
#40
1!
0#
1"
#60
1#
#80
0!
1$
0#
0"
#100
1!
1#
#120
0!
0#
1"
#140
1!
1#
