uart/uart_tx.v
// // ====================================================================
// //                 第一版，伟大尝试，出错很多，不建议使用
// // ====================================================================


// `timescale 1ns / 1ns

// // ----------------------------------------------------------------
// // Module   : uart_tx
// // Author   : 平の路
// // Function :第一版
// // ----------------------------------------------------------------

// module uart_tx #(
//     parameter integer CLK_FREQ   = 50_000_000, // 系统时钟频率 (默认 50MHz)
//     parameter integer BAUD_RATE   = 9600, // 波特率
//     parameter [7:0] UART_TX_DATA   = 0000_0000, // 数据
//     parameter integer SEND_FREQ = 1     //发送频率
// )(

//     input  wire clk,      // 系统时钟
//     input  wire rst_n,    // 低电平异步复位
//     output reg tx        // 用户输出端口
// );
// //=================================================================
// //线形序列机，串口发送，1起始位，8数据位，1结束位
// //=================================================================

//     localparam integer BAUD_CNT_MAX = CLK_FREQ/BAUD_RATE-1;//波特率->波特计数最大值(时钟频率/波特率)
//     localparam integer SEND_FREQ_CNT = CLK_FREQ/SEND_FREQ-1;//波特率->波特计数最大值(时钟频率/发送频率)

//     reg [3:0]bit_cnt;       //数据位计数器（0～9）
//     reg [15:0]baud_cnt;     //波特率计数器（记到BAUD_CNT_MAX）（9600波特率记到5208）
//     reg [25:0]tim_cnt;      //发送频率计数器，记满开始发送
//     wire baud_clk;          //波特时钟，每过一个波特时间翻转
//     reg tx_state;           //tx状态标志，0为等待发送，1为正在发送
//     reg [7:0]tx_data_r;          //数据寄存器，防止在发送过程中修改数据

//     always @(posedge clk or negedge rst_n)      //SEND_FREQ计时器，记满开始发送
//         begin
//             if (!rst_n)
//                 begin
//                     tim_cnt <= 0;
//                     tx_data_r<=0;
//                     tx_state<=0;
//                 end
//             else if(tim_cnt==SEND_FREQ_CNT)
//                 begin
//                     tim_cnt<=0;
//                     tx_data_r<=UART_TX_DATA;
//                     tx_state<=1;
//                 end
//             else
//                 tim_cnt<=tim_cnt+1;
//         end

//     always @(posedge clk or negedge rst_n)      //波特计数器，记满清零
//         begin
//             if (!rst_n)
//                 begin
//                     baud_cnt<=0;
//                 end
//             else if(tx_state==1)
//                 begin
//                     if(baud_cnt==BAUD_CNT_MAX)
//                         begin
//                             baud_cnt<=0;
//                             if(bit_cnt==9)
//                                 bit_cnt<=0;
//                             else
//                                 bit_cnt<=bit_cnt+1;     //数据位计数器，波特计数器记满+1；
//                         end
//                     else
//                         baud_cnt<=baud_cnt+1;
//                 end
//             else
//                 baud_cnt<=0;
//         end

//     assign baud_clk=(baud_cnt==0 && tx_state==1);   //波特晶振，波特计数器记满翻转=1，清零再反转=0；

//     always @(posedge clk or negedge rst_n)
//         begin
//             if(!rst_n)
//                 tx<=1;
//             else if(tx_state==1 && baud_clk==1)
//                 begin
//                     case(bit_cnt)
//                         0:tx<=0;
//                         1:tx<=tx_data_r[0];
//                         2:tx<=tx_data_r[1];
//                         3:tx<=tx_data_r[2];
//                         4:tx<=tx_data_r[3];
//                         5:tx<=tx_data_r[4];
//                         6:tx<=tx_data_r[5];
//                         7:tx<=tx_data_r[6];
//                         8:tx<=tx_data_r[7];
//                         9:tx<=1;
//                         default:tx<=1;
//                     endcase
//                 end
//         end
// endmodule















//====================================================================
//                 第二版，兼容性优化，参数化了时钟频率+波特率+数据位
//====================================================================

`timescale 1ns / 1ns

// ----------------------------------------------------------------
// Module   : uart_tx
// Author   : 平の路
// Function : 只负责发送，默认空闲，通过握手接口激活后进入忙碌阶段，最后一位数据发送完成之后进入空闲状态
// ----------------------------------------------------------------
module uart_tx #(
    parameter integer CLK_FREQ = 50_000_000, // 系统时钟频率 (默认 50MHz)
    parameter integer BAUD_RATE = 9600,      //波特率
    parameter integer BIT_COUNT = 8          //数据位

)(

    input  wire i_clk,      // 系统时钟
    input  wire i_rst_n,    // 低电平异步复位
    input  wire i_tx_valid,       // 握手信号
    input wire [BIT_COUNT-1:0]i_tx_data,    //要发送的数据
    output reg o_tx,        // 串口输出值,8位数据
    output reg o_tx_ready        //状态信号
);

    // 内部信号定义
//====================================================================
//                          底层常数计算
//====================================================================
    localparam integer BAUD_CNT_MAX = CLK_FREQ/BAUD_RATE-1;


//====================================================================
//                           寄存器声明
//====================================================================
    reg [14:0]r_baud_cnt;       //位宽放大一点，兼容不同波特率
    reg [3:0] r_bit_cnt;        //数据计数器
    reg [BIT_COUNT-1:0] r_tx_data;        //数据寄存器（防止中途更改数据）


    wire w_tx_busy = ~o_tx_ready;

    wire w_baud_pulse = (r_baud_cnt==BAUD_CNT_MAX);         //波特脉冲
//====================================================================
//进程1:波特率计数器控制 (LSM 基础驱动)
//====================================================================
    always @(posedge i_clk or negedge i_rst_n)
        begin
            if(!i_rst_n)
                begin
                    r_baud_cnt<=0;
                end
            else if(w_tx_busy) begin
                if(w_baud_pulse)
                    r_baud_cnt<=0;
                else
                    r_baud_cnt<=r_baud_cnt+1;
            end
            else
                r_baud_cnt<=0;

        end

//====================================================================
//进程 2：状态流转与数据锁存
//====================================================================

    always @(posedge i_clk or negedge i_rst_n)
        begin
            if (!i_rst_n)
                begin
                    o_tx_ready<=1;      //默认拉高
                    r_bit_cnt<= 0;
                    r_tx_data<={BIT_COUNT{1'b0}};           //{N{A}} 的意思就是：把 A 这个信号，原封不动地复制 N 遍，拼在一起。
                end
            else
                begin
                    if(o_tx_ready)
                        begin
                            if(i_tx_valid)
                                begin
                                    r_bit_cnt<=0;
                                    o_tx_ready<=0;  //进入忙碌状态
                                    r_tx_data<=i_tx_data;//数据锁存
                                end
                        end
                    else
                        begin
                            if(w_baud_pulse)
                                begin
                                    if(r_bit_cnt==BIT_COUNT+1)
                                        begin
                                            r_bit_cnt<=0;
                                            o_tx_ready<=1;
                                        end
                                    else
                                        r_bit_cnt<=r_bit_cnt+1;
                                end
                        end
                end
        end




//====================================================================
//进程 3：物理引脚电平映射 (多路选择器 MUX)
//====================================================================


    always @(posedge i_clk or negedge i_rst_n)
        begin
            if (!i_rst_n)
                begin
                    o_tx <= 1;
                end
            else if(w_tx_busy)
                begin
                    if(r_bit_cnt==0)
                        o_tx<=0;
                    else if(r_bit_cnt==BIT_COUNT+1)
                        o_tx<=1;
                    else
                        o_tx<=r_tx_data[r_bit_cnt-1];
                end
            else
                o_tx<=1;
        end

endmodule
//大功告成






// //====================================================================
// //      AI完美版，加了$clog2，加了放弃了多路选择器，使用了移位寄存器
// //      优势：兼容性更强，消耗资源减少
// //====================================================================



// `timescale 1ns / 1ns

// // ----------------------------------------------------------------
// // Module   : uart_tx (Ultimate Shift-Register Version)
// // Author   : 你的金牌导师 & 平の路
// // Function : 采用 $clog2 自动位宽计算与全硬件移位寄存器架构
// // ----------------------------------------------------------------
// module uart_tx #(
//     parameter integer CLK_FREQ  = 50_000_000,
//     parameter integer BAUD_RATE = 9600,
//     parameter integer BIT_COUNT = 8
// )(
//     input  wire                 i_clk,
//     input  wire                 i_rst_n,
//     input  wire                 i_tx_valid,
//     input  wire [BIT_COUNT-1:0] i_tx_data,
//     output reg                  o_tx,
//     output reg                  o_tx_ready
// );

//     // =================================================================
//     // 底层常数与自动位宽推导 (高级参数化)
//     // =================================================================
//     localparam integer BAUD_CNT_MAX = CLK_FREQ / BAUD_RATE - 1;
//     // 魔法指令：自动推导需要的触发器数量！
//     localparam integer BAUD_WIDTH   = $clog2(BAUD_CNT_MAX + 1);

//     // =================================================================
//     // 物理寄存器声明
//     // =================================================================
//     reg [BAUD_WIDTH-1:0] r_baud_cnt; // 无论频率多少，位宽永远刚好够用，不浪费一个DFF
//     reg [3:0]            r_bit_cnt;

//     // 【架构巨变】：不再只存数据，而是存一整个“物理发送帧” (Start + Data + Stop)
//     // 位宽为：1(起始) + BIT_COUNT(数据) + 1(停止)
//     reg [BIT_COUNT+1:0]  r_tx_frame;

//     wire w_tx_busy    = ~o_tx_ready;
//     wire w_baud_pulse = (r_baud_cnt == BAUD_CNT_MAX);

//     // =================================================================
//     // 进程 1: 波特率基础节拍器 (不变)
//     // =================================================================
//     always @(posedge i_clk or negedge i_rst_n) begin
//         if (!i_rst_n) begin
//             r_baud_cnt <= {BAUD_WIDTH{1'b0}}; // 严格位宽清零
//         end else if (w_tx_busy) begin
//             if (w_baud_pulse)
//                 r_baud_cnt <= {BAUD_WIDTH{1'b0}};
//             else
//                 r_baud_cnt <= r_baud_cnt + 1'b1;
//         end else begin
//             r_baud_cnt <= {BAUD_WIDTH{1'b0}};
//         end
//     end

//     // =================================================================
//     // 进程 2 & 3 合体：状态机与流水线移位 (消灭 MUX)
//     // =================================================================
//     always @(posedge i_clk or negedge i_rst_n) begin
//         if (!i_rst_n) begin
//             o_tx_ready <= 1'b1;
//             r_bit_cnt  <= 4'd0;
//             o_tx       <= 1'b1; // 复位时，串口线必须为高电平
//             r_tx_frame <= {(BIT_COUNT+2){1'b1}};
//         end else begin
//             if (o_tx_ready) begin
//                 if (i_tx_valid) begin
//                     o_tx_ready <= 1'b0;
//                     r_bit_cnt  <= 4'd0;
//                     // 【硬件思维】：咔哒！把 起始位(0) + 数据 + 停止位(1) 瞬间焊装进流水线！
//                     r_tx_frame <= {1'b1, i_tx_data, 1'b0};
//                 end
//             end else begin
//                 if (w_baud_pulse) begin
//                     if (r_bit_cnt == BIT_COUNT + 1) begin
//                         o_tx_ready <= 1'b1; // 发送结束
//                         r_bit_cnt  <= 4'd0;
//                     end else begin
//                         r_bit_cnt  <= r_bit_cnt + 1'b1;
//                         // 【硬件思维】：物理移位！向右挤压，最高位补 1 (空闲电平)
//                         r_tx_frame <= {1'b1, r_tx_frame[BIT_COUNT+1 : 1]};
//                     end
//                 end
//             end

//             // 【极致硬件美学】：物理引脚 o_tx 永远死死地连在流水线的出口（最低位）上！
//             // 不需要任何复杂的 if-else 或 case 选择！
//             if (w_tx_busy)
//                 o_tx <= r_tx_frame[0];
//             else
//                 o_tx <= 1'b1;
//         end
//     end

// endmodule

uart/uart_tx_tb.v
`timescale 1ns / 1ns

// ----------------------------------------------------------------
// Module   : uart_tx_tb
// Author   : 平の路
// Function : 串口发送仿真
// ----------------------------------------------------------------
module uart_tx_tb ();

   //测试信号定义
    reg i_clk;     //虚拟时钟定义
    reg i_rst_n;   //虚拟复位定义
    reg [7:0]i_tx_data;
    reg i_tx_valid;
    wire o_tx;
    wire o_tx_ready;

   //模块引用+例化
uart_tx#(
    .CLK_FREQ(50_000),    //时间缩短一千倍(少了3个0)
    .BAUD_RATE(960),
    .BIT_COUNT(8)
)
uart_tx_inst0(        //这里报错不用管
    .i_clk(i_clk),
    .i_rst_n(i_rst_n),
    .i_tx_data(i_tx_data),
    .i_tx_valid(i_tx_valid),
    .o_tx(o_tx),
    .o_tx_ready(o_tx_ready)
);

   //时钟初始化
    initial i_clk=0;
    always #10 i_clk=~i_clk;     //时钟频率为50MHZ(20ns翻转一次)

    initial begin
        $dumpfile("wave.vcd");
        $dumpvars(0, uart_tx_tb);

        i_rst_n=0;
        #201;
        i_rst_n=1;
        i_tx_data=8'b1100_1100;
        i_tx_valid=1;
        #1_000_00;
        i_tx_data=8'b1100_1100;
        i_tx_valid=0;
        #1_000_00;
        i_tx_data=8'b1100_1100;
        i_tx_valid=1;
        #1_000_00;
        $finish;
    end
endmodule

uart/wave.vcd
$date
	Tue Oct  6 16:52:35 2026
$end
$version
	Icarus Verilog
$end
$timescale
	1ns
$end
$scope module uart_tx_tb $end
$var wire 1 ! o_tx_ready $end
$var wire 1 " o_tx $end
$var reg 1 # i_clk $end
$var reg 1 $ i_rst_n $end
$var reg 8 % i_tx_data [7:0] $end
$var reg 1 & i_tx_valid $end
$scope module uart_tx_inst0 $end
$var wire 1 # i_clk $end
$var wire 1 $ i_rst_n $end
$var wire 8 ' i_tx_data [7:0] $end
$var wire 1 & i_tx_valid $end
$var wire 1 ( w_tx_busy $end
$var wire 1 ) w_baud_pulse $end
$var parameter 32 * BAUD_CNT_MAX $end
$var parameter 32 + BAUD_RATE $end
$var parameter 32 , BIT_COUNT $end
$var parameter 32 - CLK_FREQ $end
$var reg 1 " o_tx $end
$var reg 1 ! o_tx_ready $end
$var reg 15 . r_baud_cnt [14:0] $end
$var reg 4 / r_bit_cnt [3:0] $end
$var reg 8 0 r_tx_data [7:0] $end
$upscope $end
$upscope $end
$enddefinitions $end
$comment Show the parameter values. $end
$dumpall
b1100001101010000 -
b1000 ,
b1111000000 +
b110011 *
$end
#0
$dumpvars
b0 0
b0 /
b0 .
0)
0(
bx '
x&
bx %
0$
0#
1"
1!
$end
#10
1#
#20
0#
#30
1#
#40
0#
#50
1#
#60
0#
#70
1#
#80
0#
#90
1#
#100
0#
#110
1#
#120
0#
#130
1#
#140
0#
#150
1#
#160
0#
#170
1#
#180
0#
#190
1#
#200
0#
#201
1&
b11001100 %
b11001100 '
1$
#210
1(
b11001100 0
0!
1#
#220
0#
#230
b1 .
0"
1#
#240
0#
#250
b10 .
1#
#260
0#
#270
b11 .
1#
#280
0#
#290
b100 .
1#
#300
0#
#310
b101 .
1#
#320
0#
#330
b110 .
1#
#340
0#
#350
b111 .
1#
#360
0#
#370
b1000 .
1#
#380
0#
#390
b1001 .
1#
#400
0#
#410
b1010 .
1#
#420
0#
#430
b1011 .
1#
#440
0#
#450
b1100 .
1#
#460
0#
#470
b1101 .
1#
#480
0#
#490
b1110 .
1#
#500
0#
#510
b1111 .
1#
#520
0#
#530
b10000 .
1#
#540
0#
#550
b10001 .
1#
#560
0#
#570
b10010 .
1#
#580
0#
#590
b10011 .
1#
#600
0#
#610
b10100 .
1#
#620
0#
#630
b10101 .
1#
#640
0#
#650
b10110 .
1#
#660
0#
#670
b10111 .
1#
#680
0#
#690
b11000 .
1#
#700
0#
#710
b11001 .
1#
#720
0#
#730
b11010 .
1#
#740
0#
#750
b11011 .
1#
#760
0#
#770
b11100 .
1#
#780
0#
#790
b11101 .
1#
#800
0#
#810
b11110 .
1#
#820
0#
#830
b11111 .
1#
#840
0#
#850
b100000 .
1#
#860
0#
#870
b100001 .
1#
#880
0#
#890
b100010 .
1#
#900
0#
#910
b100011 .
1#
#920
0#
#930
b100100 .
1#
#940
0#
#950
b100101 .
1#
#960
0#
#970
b100110 .
1#
#980
0#
#990
b100111 .
1#
#1000
0#
#1010
b101000 .
1#
#1020
0#
#1030
b101001 .
1#
#1040
0#
#1050
b101010 .
1#
#1060
0#
#1070
b101011 .
1#
#1080
0#
#1090
b101100 .
1#
#1100
0#
#1110
b101101 .
1#
#1120
0#
#1130
b101110 .
1#
#1140
0#
#1150
b101111 .
1#
#1160
0#
#1170
b110000 .
1#
#1180
0#
#1190
b110001 .
1#
#1200
0#
#1210
b110010 .
1#
#1220
0#
#1230
1)
b110011 .
1#
#1240
0#
#1250
0)
b1 /
b0 .
1#
#1260
0#
#1270
b1 .
1#
#1280
0#
#1290
b10 .
1#
#1300
0#
#1310
b11 .
1#
#1320
0#
#1330
b100 .
1#
#1340
0#
#1350
b101 .
1#
#1360
0#
#1370
b110 .
1#
#1380
0#
#1390
b111 .
1#
#1400
0#
#1410
b1000 .
1#
#1420
0#
#1430
b1001 .
1#
#1440
0#
#1450
b1010 .
1#
#1460
0#
#1470
b1011 .
1#
#1480
0#
#1490
b1100 .
1#
#1500
0#
#1510
b1101 .
1#
#1520
0#
#1530
b1110 .
1#
#1540
0#
#1550
b1111 .
1#
#1560
0#
#1570
b10000 .
1#
#1580
0#
#1590
b10001 .
1#
#1600
0#
#1610
b10010 .
1#
#1620
0#
#1630
b10011 .
1#
#1640
0#
#1650
b10100 .
1#
#1660
0#
#1670
b10101 .
1#
#1680
0#
#1690
b10110 .
1#
#1700
0#
#1710
b10111 .
1#
#1720
0#
#1730
b11000 .
1#
#1740
0#
#1750
b11001 .
1#
#1760
0#
#1770
b11010 .
1#
#1780
0#
#1790
b11011 .
1#
#1800
0#
#1810
b11100 .
1#
#1820
0#
#1830
b11101 .
1#
#1840
0#
#1850
b11110 .
1#
#1860
0#
#1870
b11111 .
1#
#1880
0#
#1890
b100000 .
1#
#1900
0#
#1910
b100001 .
1#
#1920
0#
#1930
b100010 .
1#
#1940
0#
#1950
b100011 .
1#
#1960
0#
#1970
b100100 .
1#
#1980
0#
#1990
b100101 .
1#
#2000
0#
#2010
b100110 .
1#
#2020
0#
#2030
b100111 .
1#
#2040
0#
#2050
b101000 .
1#
#2060
0#
#2070
b101001 .
1#
#2080
0#
#2090
b101010 .
1#
#2100
0#
#2110
b101011 .
1#
#2120
0#
#2130
b101100 .
1#
#2140
0#
#2150
b101101 .
1#
#2160
0#
#2170
b101110 .
1#
#2180
0#
#2190
b101111 .
1#
#2200
0#
#2210
b110000 .
1#
#2220
0#
#2230
b110001 .
1#
#2240
0#
#2250
b110010 .
1#
#2260
0#
#2270
1)
b110011 .
1#
#2280
0#
#2290
0)
b10 /
b0 .
1#
#2300
0#
#2310
b1 .
1#
#2320
0#
#2330
b10 .
1#
#2340
0#
#2350
b11 .
1#
#2360
0#
#2370
b100 .
1#
#2380
0#
#2390
b101 .
1#
#2400
0#
#2410
b110 .
1#
#2420
0#
#2430
b111 .
1#
#2440
0#
#2450
b1000 .
1#
#2460
0#
#2470
b1001 .
1#
#2480
0#
#2490
b1010 .
1#
#2500
0#
#2510
b1011 .
1#
#2520
0#
#2530
b1100 .
1#
#2540
0#
#2550
b1101 .
1#
#2560
0#
#2570
b1110 .
1#
#2580
0#
#2590
b1111 .
1#
#2600
0#
#2610
b10000 .
1#
#2620
0#
#2630
b10001 .
1#
#2640
0#
#2650
b10010 .
1#
#2660
0#
#2670
b10011 .
1#
#2680
0#
#2690
b10100 .
1#
#2700
0#
#2710
b10101 .
1#
#2720
0#
#2730
b10110 .
1#
#2740
0#
#2750
b10111 .
1#
#2760
0#
#2770
b11000 .
1#
#2780
0#
#2790
b11001 .
1#
#2800
0#
#2810
b11010 .
1#
#2820
0#
#2830
b11011 .
1#
#2840
0#
#2850
b11100 .
1#
#2860
0#
#2870
b11101 .
1#
#2880
0#
#2890
b11110 .
1#
#2900
0#
#2910
b11111 .
1#
#2920
0#
#2930
b100000 .
1#
#2940
0#
#2950
b100001 .
1#
#2960
0#
#2970
b100010 .
1#
#2980
0#
#2990
b100011 .
1#
#3000
0#
#3010
b100100 .
1#
#3020
0#
#3030
b100101 .
1#
#3040
0#
#3050
b100110 .
1#
#3060
0#
#3070
b100111 .
1#
#3080
0#
#3090
b101000 .
1#
#3100
0#
#3110
b101001 .
1#
#3120
0#
#3130
b101010 .
1#
#3140
0#
#3150
b101011 .
1#
#3160
0#
#3170
b101100 .
1#
#3180
0#
#3190
b101101 .
1#
#3200
0#
#3210
b101110 .
1#
#3220
0#
#3230
b101111 .
1#
#3240
0#
#3250
b110000 .
1#
#3260
0#
#3270
b110001 .
1#
#3280
0#
#3290
b110010 .
1#
#3300
0#
#3310
1)
b110011 .
1#
#3320
0#
#3330
0)
b11 /
b0 .
1#
#3340
0#
#3350
b1 .
1"
1#
#3360
0#
#3370
b10 .
1#
#3380
0#
#3390
b11 .
1#
#3400
0#
#3410
b100 .
1#
#3420
0#
#3430
b101 .
1#
#3440
0#
#3450
b110 .
1#
#3460
0#
#3470
b111 .
1#
#3480
0#
#3490
b1000 .
1#
#3500
0#
#3510
b1001 .
1#
#3520
0#
#3530
b1010 .
1#
#3540
0#
#3550
b1011 .
1#
#3560
0#
#3570
b1100 .
1#
#3580
0#
#3590
b1101 .
1#
#3600
0#
#3610
b1110 .
1#
#3620
0#
#3630
b1111 .
1#
#3640
0#
#3650
b10000 .
1#
#3660
0#
#3670
b10001 .
1#
#3680
0#
#3690
b10010 .
1#
#3700
0#
#3710
b10011 .
1#
#3720
0#
#3730
b10100 .
1#
#3740
0#
#3750
b10101 .
1#
#3760
0#
#3770
b10110 .
1#
#3780
0#
#3790
b10111 .
1#
#3800
0#
#3810
b11000 .
1#
#3820
0#
#3830
b11001 .
1#
#3840
0#
#3850
b11010 .
1#
#3860
0#
#3870
b11011 .
1#
#3880
0#
#3890
b11100 .
1#
#3900
0#
#3910
b11101 .
1#
#3920
0#
#3930
b11110 .
1#
#3940
0#
#3950
b11111 .
1#
#3960
0#
#3970
b100000 .
1#
#3980
0#
#3990
b100001 .
1#
#4000
0#
#4010
b100010 .
1#
#4020
0#
#4030
b100011 .
1#
#4040
0#
#4050
b100100 .
1#
#4060
0#
#4070
b100101 .
1#
#4080
0#
#4090
b100110 .
1#
#4100
0#
#4110
b100111 .
1#
#4120
0#
#4130
b101000 .
1#
#4140
0#
#4150
b101001 .
1#
#4160
0#
#4170
b101010 .
1#
#4180
0#
#4190
b101011 .
1#
#4200
0#
#4210
b101100 .
1#
#4220
0#
#4230
b101101 .
1#
#4240
0#
#4250
b101110 .
1#
#4260
0#
#4270
b101111 .
1#
#4280
0#
#4290
b110000 .
1#
#4300
0#
#4310
b110001 .
1#
#4320
0#
#4330
b110010 .
1#
#4340
0#
#4350
1)
b110011 .
1#
#4360
0#
#4370
0)
b100 /
b0 .
1#
#4380
0#
#4390
b1 .
1#
#4400
0#
#4410
b10 .
1#
#4420
0#
#4430
b11 .
1#
#4440
0#
#4450
b100 .
1#
#4460
0#
#4470
b101 .
1#
#4480
0#
#4490
b110 .
1#
#4500
0#
#4510
b111 .
1#
#4520
0#
#4530
b1000 .
1#
#4540
0#
#4550
b1001 .
1#
#4560
0#
#4570
b1010 .
1#
#4580
0#
#4590
b1011 .
1#
#4600
0#
#4610
b1100 .
1#
#4620
0#
#4630
b1101 .
1#
#4640
0#
#4650
b1110 .
1#
#4660
0#
#4670
b1111 .
1#
#4680
0#
#4690
b10000 .
1#
#4700
0#
#4710
b10001 .
1#
#4720
0#
#4730
b10010 .
1#
#4740
0#
#4750
b10011 .
1#
#4760
0#
#4770
b10100 .
1#
#4780
0#
#4790
b10101 .
1#
#4800
0#
#4810
b10110 .
1#
#4820
0#
#4830
b10111 .
1#
#4840
0#
#4850
b11000 .
1#
#4860
0#
#4870
b11001 .
1#
#4880
0#
#4890
b11010 .
1#
#4900
0#
#4910
b11011 .
1#
#4920
0#
#4930
b11100 .
1#
#4940
0#
#4950
b11101 .
1#
#4960
0#
#4970
b11110 .
1#
#4980
0#
#4990
b11111 .
1#
#5000
0#
#5010
b100000 .
1#
#5020
0#
#5030
b100001 .
1#
#5040
0#
#5050
b100010 .
1#
#5060
0#
#5070
b100011 .
1#
#5080
0#
#5090
b100100 .
1#
#5100
0#
#5110
b100101 .
1#
#5120
0#
#5130
b100110 .
1#
#5140
0#
#5150
b100111 .
1#
#5160
0#
#5170
b101000 .
1#
#5180
0#
#5190
b101001 .
1#
#5200
0#
#5210
b101010 .
1#
#5220
0#
#5230
b101011 .
1#
#5240
0#
#5250
b101100 .
1#
#5260
0#
#5270
b101101 .
1#
#5280
0#
#5290
b101110 .
1#
#5300
0#
#5310
b101111 .
1#
#5320
0#
#5330
b110000 .
1#
#5340
0#
#5350
b110001 .
1#
#5360
0#
#5370
b110010 .
1#
#5380
0#
#5390
1)
b110011 .
1#
#5400
0#
#5410
0)
b101 /
b0 .
1#
#5420
0#
#5430
b1 .
0"
1#
#5440
0#
#5450
b10 .
1#
#5460
0#
#5470
b11 .
1#
#5480
0#
#5490
b100 .
1#
#5500
0#
#5510
b101 .
1#
#5520
0#
#5530
b110 .
1#
#5540
0#
#5550
b111 .
1#
#5560
0#
#5570
b1000 .
1#
#5580
0#
#5590
b1001 .
1#
#5600
0#
#5610
b1010 .
1#
#5620
0#
#5630
b1011 .
1#
#5640
0#
#5650
b1100 .
1#
#5660
0#
#5670
b1101 .
1#
#5680
0#
#5690
b1110 .
1#
#5700
0#
#5710
b1111 .
1#
#5720
0#
#5730
b10000 .
1#
#5740
0#
#5750
b10001 .
1#
#5760
0#
#5770
b10010 .
1#
#5780
0#
#5790
b10011 .
1#
#5800
0#
#5810
b10100 .
1#
#5820
0#
#5830
b10101 .
1#
#5840
0#
#5850
b10110 .
1#
#5860
0#
#5870
b10111 .
1#
#5880
0#
#5890
b11000 .
1#
#5900
0#
#5910
b11001 .
1#
#5920
0#
#5930
b11010 .
1#
#5940
0#
#5950
b11011 .
1#
#5960
0#
#5970
b11100 .
1#
#5980
0#
#5990
b11101 .
1#
#6000
0#
#6010
b11110 .
1#
#6020
0#
#6030
b11111 .
1#
#6040
0#
#6050
b100000 .
1#
#6060
0#
#6070
b100001 .
1#
#6080
0#
#6090
b100010 .
1#
#6100
0#
#6110
b100011 .
1#
#6120
0#
#6130
b100100 .
1#
#6140
0#
#6150
b100101 .
1#
#6160
0#
#6170
b100110 .
1#
#6180
0#
#6190
b100111 .
1#
#6200
0#
#6210
b101000 .
1#
#6220
0#
#6230
b101001 .
1#
#6240
0#
#6250
b101010 .
1#
#6260
0#
#6270
b101011 .
1#
#6280
0#
#6290
b101100 .
1#
#6300
0#
#6310
b101101 .
1#
#6320
0#
#6330
b101110 .
1#
#6340
0#
#6350
b101111 .
1#
#6360
0#
#6370
b110000 .
1#
#6380
0#
#6390
b110001 .
1#
#6400
0#
#6410
b110010 .
1#
#6420
0#
#6430
1)
b110011 .
1#
#6440
0#
#6450
0)
b110 /
b0 .
1#
#6460
0#
#6470
b1 .
1#
#6480
0#
#6490
b10 .
1#
#6500
0#
#6510
b11 .
1#
#6520
0#
#6530
b100 .
1#
#6540
0#
#6550
b101 .
1#
#6560
0#
#6570
b110 .
1#
#6580
0#
#6590
b111 .
1#
#6600
0#
#6610
b1000 .
1#
#6620
0#
#6630
b1001 .
1#
#6640
0#
#6650
b1010 .
1#
#6660
0#
#6670
b1011 .
1#
#6680
0#
#6690
b1100 .
1#
#6700
0#
#6710
b1101 .
1#
#6720
0#
#6730
b1110 .
1#
#6740
0#
#6750
b1111 .
1#
#6760
0#
#6770
b10000 .
1#
#6780
0#
#6790
b10001 .
1#
#6800
0#
#6810
b10010 .
1#
#6820
0#
#6830
b10011 .
1#
#6840
0#
#6850
b10100 .
1#
#6860
0#
#6870
b10101 .
1#
#6880
0#
#6890
b10110 .
1#
#6900
0#
#6910
b10111 .
1#
#6920
0#
#6930
b11000 .
1#
#6940
0#
#6950
b11001 .
1#
#6960
0#
#6970
b11010 .
1#
#6980
0#
#6990
b11011 .
1#
#7000
0#
#7010
b11100 .
1#
#7020
0#
#7030
b11101 .
1#
#7040
0#
#7050
b11110 .
1#
#7060
0#
#7070
b11111 .
1#
#7080
0#
#7090
b100000 .
1#
#7100
0#
#7110
b100001 .
1#
#7120
0#
#7130
b100010 .
1#
#7140
0#
#7150
b100011 .
1#
#7160
0#
#7170
b100100 .
1#
#7180
0#
#7190
b100101 .
1#
#7200
0#
#7210
b100110 .
1#
#7220
0#
#7230
b100111 .
1#
#7240
0#
#7250
b101000 .
1#
#7260
0#
#7270
b101001 .
1#
#7280
0#
#7290
b101010 .
1#
#7300
0#
#7310
b101011 .
1#
#7320
0#
#7330
b101100 .
1#
#7340
0#
#7350
b101101 .
1#
#7360
0#
#7370
b101110 .
1#
#7380
0#
#7390
b101111 .
1#
#7400
0#
#7410
b110000 .
1#
#7420
0#
#7430
b110001 .
1#
#7440
0#
#7450
b110010 .
1#
#7460
0#
#7470
1)
b110011 .
1#
#7480
0#
#7490
0)
b111 /
b0 .
1#
#7500
0#
#7510
b1 .
1"
1#
#7520
0#
#7530
b10 .
1#
#7540
0#
#7550
b11 .
1#
#7560
0#
#7570
b100 .
1#
#7580
0#
#7590
b101 .
1#
#7600
0#
#7610
b110 .
1#
#7620
0#
#7630
b111 .
1#
#7640
0#
#7650
b1000 .
1#
#7660
0#
#7670
b1001 .
1#
#7680
0#
#7690
b1010 .
1#
#7700
0#
#7710
b1011 .
1#
#7720
0#
#7730
b1100 .
1#
#7740
0#
#7750
b1101 .
1#
#7760
0#
#7770
b1110 .
1#
#7780
0#
#7790
b1111 .
1#
#7800
0#
#7810
b10000 .
1#
#7820
0#
#7830
b10001 .
1#
#7840
0#
#7850
b10010 .
1#
#7860
0#
#7870
b10011 .
1#
#7880
0#
#7890
b10100 .
1#
#7900
0#
#7910
b10101 .
1#
#7920
0#
#7930
b10110 .
1#
#7940
0#
#7950
b10111 .
1#
#7960
0#
#7970
b11000 .
1#
#7980
0#
#7990
b11001 .
1#
#8000
0#
#8010
b11010 .
1#
#8020
0#
#8030
b11011 .
1#
#8040
0#
#8050
b11100 .
1#
#8060
0#
#8070
b11101 .
1#
#8080
0#
#8090
b11110 .
1#
#8100
0#
#8110
b11111 .
1#
#8120
0#
#8130
b100000 .
1#
#8140
0#
#8150
b100001 .
1#
#8160
0#
#8170
b100010 .
1#
#8180
0#
#8190
b100011 .
1#
#8200
0#
#8210
b100100 .
1#
#8220
0#
#8230
b100101 .
1#
#8240
0#
#8250
b100110 .
1#
#8260
0#
#8270
b100111 .
1#
#8280
0#
#8290
b101000 .
1#
#8300
0#
#8310
b101001 .
1#
#8320
0#
#8330
b101010 .
1#
#8340
0#
#8350
b101011 .
1#
#8360
0#
#8370
b101100 .
1#
#8380
0#
#8390
b101101 .
1#
#8400
0#
#8410
b101110 .
1#
#8420
0#
#8430
b101111 .
1#
#8440
0#
#8450
b110000 .
1#
#8460
0#
#8470
b110001 .
1#
#8480
0#
#8490
b110010 .
1#
#8500
0#
#8510
1)
b110011 .
1#
#8520
0#
#8530
0)
b1000 /
b0 .
1#
#8540
0#
#8550
b1 .
1#
#8560
0#
#8570
b10 .
1#
#8580
0#
#8590
b11 .
1#
#8600
0#
#8610
b100 .
1#
#8620
0#
#8630
b101 .
1#
#8640
0#
#8650
b110 .
1#
#8660
0#
#8670
b111 .
1#
#8680
0#
#8690
b1000 .
1#
#8700
0#
#8710
b1001 .
1#
#8720
0#
#8730
b1010 .
1#
#8740
0#
#8750
b1011 .
1#
#8760
0#
#8770
b1100 .
1#
#8780
0#
#8790
b1101 .
1#
#8800
0#
#8810
b1110 .
1#
#8820
0#
#8830
b1111 .
1#
#8840
0#
